Metadata-Version: 1.2
Name: django-blend
Version: 0.0.0
Summary:  Provides convention-over-configuration for your Django projects
Home-page: https://github.com/metanic/django-blend
Author: Bailey "monokrome" Stoner
Author-email: monokrome@monokro.me
Maintainer: Bailey "monokrome" Stoner
Maintainer-email: monokrome@monokro.me
License: BSD 3-Clause License
Platform: UNKNOWN
